napari_mclabel/__init__.py
napari_mclabel/_version.py
napari_mclabel/mclabel.py
napari_mclabel/utils.py
napari_mclabel-1.0.1.dev0.dist-info/METADATA
napari_mclabel-1.0.1.dev0.dist-info/WHEEL
napari_mclabel-1.0.1.dev0.dist-info/entry_points.txt
napari_mclabel-1.0.1.dev0.dist-info/top_level.txt
napari_mclabel-1.0.1.dev0.dist-info/RECORD
