Metadata-Version: 2.1
Name: napari-mclabel
Version: 1.0.1.dev0
Summary: Napari plugin for semi-automatic labeling of macrophages
Home-page: https://gitlab.cs.fau.de/xo04syge/mclabel
Author: Jonas Utz
Author-email: jonas.utz@fau.de
License: BSD-3-Clause
Project-URL: Bug Tracker, https://gitlab.cs.fau.de/xo04syge/mclabel/-/issues
Project-URL: Documentation, https://gitlab.cs.fau.de/xo04syge/mclabel/-/blob/main/README.md
Project-URL: Source Code, https://gitlab.cs.fau.de/xo04syge/mclabel
Project-URL: User Support, https://gitlab.cs.fau.de/xo04syge/mclabel/-/issues
Classifier: Development Status :: 2 - Pre-Alpha
Classifier: Framework :: napari
Classifier: Topic :: Software Development :: Testing
Classifier: Programming Language :: Python
Classifier: Programming Language :: Python :: 3
Classifier: Programming Language :: Python :: 3.8
Classifier: Programming Language :: Python :: 3.9
Classifier: Programming Language :: Python :: 3.10
Classifier: Operating System :: OS Independent
Classifier: License :: OSI Approved :: BSD License
Requires-Python: >=3.8
Requires-Dist: napari[all]
Requires-Dist: napari-plugin-engine (>=0.1.4)
Requires-Dist: imaris-ims-file-reader (>=0.1.5)
Requires-Dist: numpy
Requires-Dist: h5py
Requires-Dist: dask
Requires-Dist: napari-imaris-loader
Requires-Dist: scikit-image
Requires-Dist: scipy
